ECE 350/Stuffs/Lab 3/mux_2.v
module mux_2 (
    out,
    select,
    in0,
    in1
);
    
    input select;
    input in0, in1;

    output out;

    assign out = select ? in1 : in0;

endmodule

ECE 350/Stuffs/Lab 3/mux_4.v
module mux_4 (
    out,
    select,
    in0,
    in1,
    in2,
    in3
);
    
    input [1:0]select;
    input in0, in1, in2, in3;

    output out;

    wire w1, w2;

    mux_2 l1_1(w1, select[0], in0, in1);
    mux_2 l1_2(w2, select[0], in2, in3);

    mux_2 l2_1(out, select[1], w1, w2);

endmodule

ECE 350/Stuffs/Lab 3/mux_8.v
module mux_8 (
    out,
    select,
    in0,
    in1,
    in2,
    in3,
    in4,
    in5,
    in6,
    in7
);
    
    input [2:0]select;
    input in0, in1, in2, in3, in4, in5, in6, in7;

    output out;

    wire w1, w2;

    mux_4 l1_1(w1, select[1:0], in0, in1, in2, in3);
    mux_4 l1_2(w2, select[1:0], in4, in5, in6, in7);

    mux_2 l2_1(out, select[2], w1, w2);

endmodule

ECE 350/Stuffs/Lab 3/comp_2.v
module comp_2(EQ1, GT1, A, B, EQ0, GT0);
    input EQ1, GT1;
    input [1:0] A, B;
    output EQ0, GT0;


    //notA and notB
    wire[1:0] notA, notB;

    not n1(notA[1], A[1]);
    not n2(notA[0], A[0]);
    not n3(notB[1], B[1]);
    not n4(notB[0], B[0]);

    wire[2:0] selectBits;

    assign selectBits[2] = A[1];
    assign selectBits[1] = A[0];
    assign selectBits[0] = B[1];

    wire eqmux, gtmux;
    
    mux_8 EQout(eqmux, selectBits, notB[0], 1'b0, B[0], 1'b0, 1'b0, notB[0], 1'b0, B[0]);

    mux_8 GTout(gtmux, selectBits, 1'b0, 1'b0, notB[0], 1'b0, 1'b1, 1'b0, 1'b1, notB[0]);


    //evaluating EQ_out
    wire EQandnotGTin, notGT1, notEQ1;

    not notGTinand(notGT1, GT1);
    not notEQinand(notEQ1, EQ1);

    wire EQ1andnotGT1forEQ0;


    and jeronimo(EQ0, eqmux, EQ1, notGT1);

    wire justin, smith;

    and jj(justin, gtmux, EQ1, notGT1);
    and ss(smith, notEQ1, GT1);

    or suckItBozo(GT0, justin, smith);

endmodule

ECE 350/Stuffs/Lab 3/comp_8.v
module comp_8(EQ1, GT1, A, B, EQ0, GT0);
    input EQ1, GT1;
    input [7:0] A, B;
    output EQ0, GT0;

    wire a, apple;
    comp_2 sally(.EQ1(EQ1), .GT1(GT1), .A(A[7:6]), .B(B[7:6]), .EQ0(a), .GT0(apple));

    wire bartholemew, boy;
    comp_2 bozo(.EQ1(a), .GT1(apple), .A(A[5:4]), .B(B[5:4]), .EQ0(bartholemew), .GT0(boy));

    wire crumbs, crumbss;
    comp_2 crumbsss(.EQ1(bartholemew), .GT1(boy), .A(A[3:2]), .B(B[3:2]), .EQ0(crumbs), .GT0(crumbss));

    comp_2 drockmortonIII(.EQ1(crumbs), .GT1(crumbss), .A(A[1:0]), .B(B[1:0]), .EQ0(EQ0), .GT0(GT0));

endmodule

ECE 350/Stuffs/Lab 3/comp_2_tb.v
module comp_2_tb;
    wire [7:0] A, B;
    wire EQ1, GT1;
    wire EQ0, GT0;

    comp_8 c1(.EQ1(EQ1), .GT1(GT1), .A(A), .B(B), .EQ0(EQ0), .GT0(GT0));

    integer i;
    assign {A, B, EQ1, GT1} = i;


    initial begin
        for (i = 0; i < 256; i = i + 1) begin
            #20;
            $display("A = %b, B = %b, EQ0 = %b, GT0 = %b, EQ1 = %b, GT1 = %b", A, B, EQ0, GT0, EQ1, GT1);
        end
        $finish;
    end

    initial begin
        $dumpfile("comp_2_tb.vcd");
        $dumpvars(0, comp_2_tb);
    end
endmodule

ECE 350/Stuffs/Lab 3/comp_2_tb.vcd
$date
	Fri Feb  2 11:49:18 2024
$end
$version
	Icarus Verilog
$end
$timescale
	1s
$end
$scope module comp_2_tb $end
$var wire 1 ! GT1 $end
$var wire 1 " GT0 $end
$var wire 1 # EQ1 $end
$var wire 1 $ EQ0 $end
$var wire 8 % B [7:0] $end
$var wire 8 & A [7:0] $end
$var integer 32 ' i [31:0] $end
$scope module c1 $end
$var wire 8 ( A [7:0] $end
$var wire 8 ) B [7:0] $end
$var wire 1 # EQ1 $end
$var wire 1 ! GT1 $end
$var wire 1 * crumbss $end
$var wire 1 + crumbs $end
$var wire 1 , boy $end
$var wire 1 - bartholemew $end
$var wire 1 . apple $end
$var wire 1 / a $end
$var wire 1 " GT0 $end
$var wire 1 $ EQ0 $end
$scope module bozo $end
$var wire 2 0 A [1:0] $end
$var wire 2 1 B [1:0] $end
$var wire 1 - EQ0 $end
$var wire 1 , GT0 $end
$var wire 1 2 justin $end
$var wire 1 3 notEQ1 $end
$var wire 1 4 notGT1 $end
$var wire 1 5 smith $end
$var wire 3 6 selectBits [2:0] $end
$var wire 2 7 notB [1:0] $end
$var wire 2 8 notA [1:0] $end
$var wire 1 9 gtmux $end
$var wire 1 : eqmux $end
$var wire 1 . GT1 $end
$var wire 1 / EQ1 $end
$scope module EQout $end
$var wire 1 ; in0 $end
$var wire 1 < in1 $end
$var wire 1 = in2 $end
$var wire 1 > in3 $end
$var wire 1 ? in4 $end
$var wire 1 @ in5 $end
$var wire 1 A in6 $end
$var wire 1 B in7 $end
$var wire 3 C select [2:0] $end
$var wire 1 D w2 $end
$var wire 1 E w1 $end
$var wire 1 : out $end
$scope module l1_1 $end
$var wire 1 ; in0 $end
$var wire 1 < in1 $end
$var wire 1 = in2 $end
$var wire 1 > in3 $end
$var wire 2 F select [1:0] $end
$var wire 1 G w2 $end
$var wire 1 H w1 $end
$var wire 1 E out $end
$scope module l1_1 $end
$var wire 1 ; in0 $end
$var wire 1 < in1 $end
$var wire 1 I select $end
$var wire 1 H out $end
$upscope $end
$scope module l1_2 $end
$var wire 1 = in0 $end
$var wire 1 > in1 $end
$var wire 1 J select $end
$var wire 1 G out $end
$upscope $end
$scope module l2_1 $end
$var wire 1 H in0 $end
$var wire 1 G in1 $end
$var wire 1 K select $end
$var wire 1 E out $end
$upscope $end
$upscope $end
$scope module l1_2 $end
$var wire 1 ? in0 $end
$var wire 1 @ in1 $end
$var wire 1 A in2 $end
$var wire 1 B in3 $end
$var wire 2 L select [1:0] $end
$var wire 1 M w2 $end
$var wire 1 N w1 $end
$var wire 1 D out $end
$scope module l1_1 $end
$var wire 1 ? in0 $end
$var wire 1 @ in1 $end
$var wire 1 O select $end
$var wire 1 N out $end
$upscope $end
$scope module l1_2 $end
$var wire 1 A in0 $end
$var wire 1 B in1 $end
$var wire 1 P select $end
$var wire 1 M out $end
$upscope $end
$scope module l2_1 $end
$var wire 1 N in0 $end
$var wire 1 M in1 $end
$var wire 1 Q select $end
$var wire 1 D out $end
$upscope $end
$upscope $end
$scope module l2_1 $end
$var wire 1 E in0 $end
$var wire 1 D in1 $end
$var wire 1 R select $end
$var wire 1 : out $end
$upscope $end
$upscope $end
$scope module GTout $end
$var wire 1 S in0 $end
$var wire 1 T in1 $end
$var wire 1 U in2 $end
$var wire 1 V in3 $end
$var wire 1 W in4 $end
$var wire 1 X in5 $end
$var wire 1 Y in6 $end
$var wire 1 Z in7 $end
$var wire 3 [ select [2:0] $end
$var wire 1 \ w2 $end
$var wire 1 ] w1 $end
$var wire 1 9 out $end
$scope module l1_1 $end
$var wire 1 S in0 $end
$var wire 1 T in1 $end
$var wire 1 U in2 $end
$var wire 1 V in3 $end
$var wire 2 ^ select [1:0] $end
$var wire 1 _ w2 $end
$var wire 1 ` w1 $end
$var wire 1 ] out $end
$scope module l1_1 $end
$var wire 1 S in0 $end
$var wire 1 T in1 $end
$var wire 1 a select $end
$var wire 1 ` out $end
$upscope $end
$scope module l1_2 $end
$var wire 1 U in0 $end
$var wire 1 V in1 $end
$var wire 1 b select $end
$var wire 1 _ out $end
$upscope $end
$scope module l2_1 $end
$var wire 1 ` in0 $end
$var wire 1 _ in1 $end
$var wire 1 c select $end
$var wire 1 ] out $end
$upscope $end
$upscope $end
$scope module l1_2 $end
$var wire 1 W in0 $end
$var wire 1 X in1 $end
$var wire 1 Y in2 $end
$var wire 1 Z in3 $end
$var wire 2 d select [1:0] $end
$var wire 1 e w2 $end
$var wire 1 f w1 $end
$var wire 1 \ out $end
$scope module l1_1 $end
$var wire 1 W in0 $end
$var wire 1 X in1 $end
$var wire 1 g select $end
$var wire 1 f out $end
$upscope $end
$scope module l1_2 $end
$var wire 1 Y in0 $end
$var wire 1 Z in1 $end
$var wire 1 h select $end
$var wire 1 e out $end
$upscope $end
$scope module l2_1 $end
$var wire 1 f in0 $end
$var wire 1 e in1 $end
$var wire 1 i select $end
$var wire 1 \ out $end
$upscope $end
$upscope $end
$scope module l2_1 $end
$var wire 1 ] in0 $end
$var wire 1 \ in1 $end
$var wire 1 j select $end
$var wire 1 9 out $end
$upscope $end
$upscope $end
$upscope $end
$scope module crumbsss $end
$var wire 2 k A [1:0] $end
$var wire 2 l B [1:0] $end
$var wire 1 + EQ0 $end
$var wire 1 - EQ1 $end
$var wire 1 * GT0 $end
$var wire 1 , GT1 $end
$var wire 1 m justin $end
$var wire 1 n notEQ1 $end
$var wire 1 o notGT1 $end
$var wire 1 p smith $end
$var wire 3 q selectBits [2:0] $end
$var wire 2 r notB [1:0] $end
$var wire 2 s notA [1:0] $end
$var wire 1 t gtmux $end
$var wire 1 u eqmux $end
$scope module EQout $end
$var wire 1 v in0 $end
$var wire 1 w in1 $end
$var wire 1 x in2 $end
$var wire 1 y in3 $end
$var wire 1 z in4 $end
$var wire 1 { in5 $end
$var wire 1 | in6 $end
$var wire 1 } in7 $end
$var wire 3 ~ select [2:0] $end
$var wire 1 !" w2 $end
$var wire 1 "" w1 $end
$var wire 1 u out $end
$scope module l1_1 $end
$var wire 1 v in0 $end
$var wire 1 w in1 $end
$var wire 1 x in2 $end
$var wire 1 y in3 $end
$var wire 2 #" select [1:0] $end
$var wire 1 $" w2 $end
$var wire 1 %" w1 $end
$var wire 1 "" out $end
$scope module l1_1 $end
$var wire 1 v in0 $end
$var wire 1 w in1 $end
$var wire 1 &" select $end
$var wire 1 %" out $end
$upscope $end
$scope module l1_2 $end
$var wire 1 x in0 $end
$var wire 1 y in1 $end
$var wire 1 '" select $end
$var wire 1 $" out $end
$upscope $end
$scope module l2_1 $end
$var wire 1 %" in0 $end
$var wire 1 $" in1 $end
$var wire 1 (" select $end
$var wire 1 "" out $end
$upscope $end
$upscope $end
$scope module l1_2 $end
$var wire 1 z in0 $end
$var wire 1 { in1 $end
$var wire 1 | in2 $end
$var wire 1 } in3 $end
$var wire 2 )" select [1:0] $end
$var wire 1 *" w2 $end
$var wire 1 +" w1 $end
$var wire 1 !" out $end
$scope module l1_1 $end
$var wire 1 z in0 $end
$var wire 1 { in1 $end
$var wire 1 ," select $end
$var wire 1 +" out $end
$upscope $end
$scope module l1_2 $end
$var wire 1 | in0 $end
$var wire 1 } in1 $end
$var wire 1 -" select $end
$var wire 1 *" out $end
$upscope $end
$scope module l2_1 $end
$var wire 1 +" in0 $end
$var wire 1 *" in1 $end
$var wire 1 ." select $end
$var wire 1 !" out $end
$upscope $end
$upscope $end
$scope module l2_1 $end
$var wire 1 "" in0 $end
$var wire 1 !" in1 $end
$var wire 1 /" select $end
$var wire 1 u out $end
$upscope $end
$upscope $end
$scope module GTout $end
$var wire 1 0" in0 $end
$var wire 1 1" in1 $end
$var wire 1 2" in2 $end
$var wire 1 3" in3 $end
$var wire 1 4" in4 $end
$var wire 1 5" in5 $end
$var wire 1 6" in6 $end
$var wire 1 7" in7 $end
$var wire 3 8" select [2:0] $end
$var wire 1 9" w2 $end
$var wire 1 :" w1 $end
$var wire 1 t out $end
$scope module l1_1 $end
$var wire 1 0" in0 $end
$var wire 1 1" in1 $end
$var wire 1 2" in2 $end
$var wire 1 3" in3 $end
$var wire 2 ;" select [1:0] $end
$var wire 1 <" w2 $end
$var wire 1 =" w1 $end
$var wire 1 :" out $end
$scope module l1_1 $end
$var wire 1 0" in0 $end
$var wire 1 1" in1 $end
$var wire 1 >" select $end
$var wire 1 =" out $end
$upscope $end
$scope module l1_2 $end
$var wire 1 2" in0 $end
$var wire 1 3" in1 $end
$var wire 1 ?" select $end
$var wire 1 <" out $end
$upscope $end
$scope module l2_1 $end
$var wire 1 =" in0 $end
$var wire 1 <" in1 $end
$var wire 1 @" select $end
$var wire 1 :" out $end
$upscope $end
$upscope $end
$scope module l1_2 $end
$var wire 1 4" in0 $end
$var wire 1 5" in1 $end
$var wire 1 6" in2 $end
$var wire 1 7" in3 $end
$var wire 2 A" select [1:0] $end
$var wire 1 B" w2 $end
$var wire 1 C" w1 $end
$var wire 1 9" out $end
$scope module l1_1 $end
$var wire 1 4" in0 $end
$var wire 1 5" in1 $end
$var wire 1 D" select $end
$var wire 1 C" out $end
$upscope $end
$scope module l1_2 $end
$var wire 1 6" in0 $end
$var wire 1 7" in1 $end
$var wire 1 E" select $end
$var wire 1 B" out $end
$upscope $end
$scope module l2_1 $end
$var wire 1 C" in0 $end
$var wire 1 B" in1 $end
$var wire 1 F" select $end
$var wire 1 9" out $end
$upscope $end
$upscope $end
$scope module l2_1 $end
$var wire 1 :" in0 $end
$var wire 1 9" in1 $end
$var wire 1 G" select $end
$var wire 1 t out $end
$upscope $end
$upscope $end
$upscope $end
$scope module drockmortonIII $end
$var wire 2 H" A [1:0] $end
$var wire 2 I" B [1:0] $end
$var wire 1 $ EQ0 $end
$var wire 1 + EQ1 $end
$var wire 1 " GT0 $end
$var wire 1 * GT1 $end
$var wire 1 J" justin $end
$var wire 1 K" notEQ1 $end
$var wire 1 L" notGT1 $end
$var wire 1 M" smith $end
$var wire 3 N" selectBits [2:0] $end
$var wire 2 O" notB [1:0] $end
$var wire 2 P" notA [1:0] $end
$var wire 1 Q" gtmux $end
$var wire 1 R" eqmux $end
$scope module EQout $end
$var wire 1 S" in0 $end
$var wire 1 T" in1 $end
$var wire 1 U" in2 $end
$var wire 1 V" in3 $end
$var wire 1 W" in4 $end
$var wire 1 X" in5 $end
$var wire 1 Y" in6 $end
$var wire 1 Z" in7 $end
$var wire 3 [" select [2:0] $end
$var wire 1 \" w2 $end
$var wire 1 ]" w1 $end
$var wire 1 R" out $end
$scope module l1_1 $end
$var wire 1 S" in0 $end
$var wire 1 T" in1 $end
$var wire 1 U" in2 $end
$var wire 1 V" in3 $end
$var wire 2 ^" select [1:0] $end
$var wire 1 _" w2 $end
$var wire 1 `" w1 $end
$var wire 1 ]" out $end
$scope module l1_1 $end
$var wire 1 S" in0 $end
$var wire 1 T" in1 $end
$var wire 1 a" select $end
$var wire 1 `" out $end
$upscope $end
$scope module l1_2 $end
$var wire 1 U" in0 $end
$var wire 1 V" in1 $end
$var wire 1 b" select $end
$var wire 1 _" out $end
$upscope $end
$scope module l2_1 $end
$var wire 1 `" in0 $end
$var wire 1 _" in1 $end
$var wire 1 c" select $end
$var wire 1 ]" out $end
$upscope $end
$upscope $end
$scope module l1_2 $end
$var wire 1 W" in0 $end
$var wire 1 X" in1 $end
$var wire 1 Y" in2 $end
$var wire 1 Z" in3 $end
$var wire 2 d" select [1:0] $end
$var wire 1 e" w2 $end
$var wire 1 f" w1 $end
$var wire 1 \" out $end
$scope module l1_1 $end
$var wire 1 W" in0 $end
$var wire 1 X" in1 $end
$var wire 1 g" select $end
$var wire 1 f" out $end
$upscope $end
$scope module l1_2 $end
$var wire 1 Y" in0 $end
$var wire 1 Z" in1 $end
$var wire 1 h" select $end
$var wire 1 e" out $end
$upscope $end
$scope module l2_1 $end
$var wire 1 f" in0 $end
$var wire 1 e" in1 $end
$var wire 1 i" select $end
$var wire 1 \" out $end
$upscope $end
$upscope $end
$scope module l2_1 $end
$var wire 1 ]" in0 $end
$var wire 1 \" in1 $end
$var wire 1 j" select $end
$var wire 1 R" out $end
$upscope $end
$upscope $end
$scope module GTout $end
$var wire 1 k" in0 $end
$var wire 1 l" in1 $end
$var wire 1 m" in2 $end
$var wire 1 n" in3 $end
$var wire 1 o" in4 $end
$var wire 1 p" in5 $end
$var wire 1 q" in6 $end
$var wire 1 r" in7 $end
$var wire 3 s" select [2:0] $end
$var wire 1 t" w2 $end
$var wire 1 u" w1 $end
$var wire 1 Q" out $end
$scope module l1_1 $end
$var wire 1 k" in0 $end
$var wire 1 l" in1 $end
$var wire 1 m" in2 $end
$var wire 1 n" in3 $end
$var wire 2 v" select [1:0] $end
$var wire 1 w" w2 $end
$var wire 1 x" w1 $end
$var wire 1 u" out $end
$scope module l1_1 $end
$var wire 1 k" in0 $end
$var wire 1 l" in1 $end
$var wire 1 y" select $end
$var wire 1 x" out $end
$upscope $end
$scope module l1_2 $end
$var wire 1 m" in0 $end
$var wire 1 n" in1 $end
$var wire 1 z" select $end
$var wire 1 w" out $end
$upscope $end
$scope module l2_1 $end
$var wire 1 x" in0 $end
$var wire 1 w" in1 $end
$var wire 1 {" select $end
$var wire 1 u" out $end
$upscope $end
$upscope $end
$scope module l1_2 $end
$var wire 1 o" in0 $end
$var wire 1 p" in1 $end
$var wire 1 q" in2 $end
$var wire 1 r" in3 $end
$var wire 2 |" select [1:0] $end
$var wire 1 }" w2 $end
$var wire 1 ~" w1 $end
$var wire 1 t" out $end
$scope module l1_1 $end
$var wire 1 o" in0 $end
$var wire 1 p" in1 $end
$var wire 1 !# select $end
$var wire 1 ~" out $end
$upscope $end
$scope module l1_2 $end
$var wire 1 q" in0 $end
$var wire 1 r" in1 $end
$var wire 1 "# select $end
$var wire 1 }" out $end
$upscope $end
$scope module l2_1 $end
$var wire 1 ~" in0 $end
$var wire 1 }" in1 $end
$var wire 1 ## select $end
$var wire 1 t" out $end
$upscope $end
$upscope $end
$scope module l2_1 $end
$var wire 1 u" in0 $end
$var wire 1 t" in1 $end
$var wire 1 $# select $end
$var wire 1 Q" out $end
$upscope $end
$upscope $end
$upscope $end
$scope module sally $end
$var wire 2 %# A [1:0] $end
$var wire 2 &# B [1:0] $end
$var wire 1 / EQ0 $end
$var wire 1 # EQ1 $end
$var wire 1 . GT0 $end
$var wire 1 ! GT1 $end
$var wire 1 '# justin $end
$var wire 1 (# notEQ1 $end
$var wire 1 )# notGT1 $end
$var wire 1 *# smith $end
$var wire 3 +# selectBits [2:0] $end
$var wire 2 ,# notB [1:0] $end
$var wire 2 -# notA [1:0] $end
$var wire 1 .# gtmux $end
$var wire 1 /# eqmux $end
$scope module EQout $end
$var wire 1 0# in0 $end
$var wire 1 1# in1 $end
$var wire 1 2# in2 $end
$var wire 1 3# in3 $end
$var wire 1 4# in4 $end
$var wire 1 5# in5 $end
$var wire 1 6# in6 $end
$var wire 1 7# in7 $end
$var wire 3 8# select [2:0] $end
$var wire 1 9# w2 $end
$var wire 1 :# w1 $end
$var wire 1 /# out $end
$scope module l1_1 $end
$var wire 1 0# in0 $end
$var wire 1 1# in1 $end
$var wire 1 2# in2 $end
$var wire 1 3# in3 $end
$var wire 2 ;# select [1:0] $end
$var wire 1 <# w2 $end
$var wire 1 =# w1 $end
$var wire 1 :# out $end
$scope module l1_1 $end
$var wire 1 0# in0 $end
$var wire 1 1# in1 $end
$var wire 1 ># select $end
$var wire 1 =# out $end
$upscope $end
$scope module l1_2 $end
$var wire 1 2# in0 $end
$var wire 1 3# in1 $end
$var wire 1 ?# select $end
$var wire 1 <# out $end
$upscope $end
$scope module l2_1 $end
$var wire 1 =# in0 $end
$var wire 1 <# in1 $end
$var wire 1 @# select $end
$var wire 1 :# out $end
$upscope $end
$upscope $end
$scope module l1_2 $end
$var wire 1 4# in0 $end
$var wire 1 5# in1 $end
$var wire 1 6# in2 $end
$var wire 1 7# in3 $end
$var wire 2 A# select [1:0] $end
$var wire 1 B# w2 $end
$var wire 1 C# w1 $end
$var wire 1 9# out $end
$scope module l1_1 $end
$var wire 1 4# in0 $end
$var wire 1 5# in1 $end
$var wire 1 D# select $end
$var wire 1 C# out $end
$upscope $end
$scope module l1_2 $end
$var wire 1 6# in0 $end
$var wire 1 7# in1 $end
$var wire 1 E# select $end
$var wire 1 B# out $end
$upscope $end
$scope module l2_1 $end
$var wire 1 C# in0 $end
$var wire 1 B# in1 $end
$var wire 1 F# select $end
$var wire 1 9# out $end
$upscope $end
$upscope $end
$scope module l2_1 $end
$var wire 1 :# in0 $end
$var wire 1 9# in1 $end
$var wire 1 G# select $end
$var wire 1 /# out $end
$upscope $end
$upscope $end
$scope module GTout $end
$var wire 1 H# in0 $end
$var wire 1 I# in1 $end
$var wire 1 J# in2 $end
$var wire 1 K# in3 $end
$var wire 1 L# in4 $end
$var wire 1 M# in5 $end
$var wire 1 N# in6 $end
$var wire 1 O# in7 $end
$var wire 3 P# select [2:0] $end
$var wire 1 Q# w2 $end
$var wire 1 R# w1 $end
$var wire 1 .# out $end
$scope module l1_1 $end
$var wire 1 H# in0 $end
$var wire 1 I# in1 $end
$var wire 1 J# in2 $end
$var wire 1 K# in3 $end
$var wire 2 S# select [1:0] $end
$var wire 1 T# w2 $end
$var wire 1 U# w1 $end
$var wire 1 R# out $end
$scope module l1_1 $end
$var wire 1 H# in0 $end
$var wire 1 I# in1 $end
$var wire 1 V# select $end
$var wire 1 U# out $end
$upscope $end
$scope module l1_2 $end
$var wire 1 J# in0 $end
$var wire 1 K# in1 $end
$var wire 1 W# select $end
$var wire 1 T# out $end
$upscope $end
$scope module l2_1 $end
$var wire 1 U# in0 $end
$var wire 1 T# in1 $end
$var wire 1 X# select $end
$var wire 1 R# out $end
$upscope $end
$upscope $end
$scope module l1_2 $end
$var wire 1 L# in0 $end
$var wire 1 M# in1 $end
$var wire 1 N# in2 $end
$var wire 1 O# in3 $end
$var wire 2 Y# select [1:0] $end
$var wire 1 Z# w2 $end
$var wire 1 [# w1 $end
$var wire 1 Q# out $end
$scope module l1_1 $end
$var wire 1 L# in0 $end
$var wire 1 M# in1 $end
$var wire 1 \# select $end
$var wire 1 [# out $end
$upscope $end
$scope module l1_2 $end
$var wire 1 N# in0 $end
$var wire 1 O# in1 $end
$var wire 1 ]# select $end
$var wire 1 Z# out $end
$upscope $end
$scope module l2_1 $end
$var wire 1 [# in0 $end
$var wire 1 Z# in1 $end
$var wire 1 ^# select $end
$var wire 1 Q# out $end
$upscope $end
$upscope $end
$scope module l2_1 $end
$var wire 1 R# in0 $end
$var wire 1 Q# in1 $end
$var wire 1 _# select $end
$var wire 1 .# out $end
$upscope $end
$upscope $end
$upscope $end
$upscope $end
$upscope $end
$enddefinitions $end
$comment Show the parameter values. $end
$dumpall
$end
#0
$dumpvars
0_#
0^#
0]#
0\#
1[#
1Z#
b0 Y#
0X#
0W#
0V#
0U#
1T#
b0 S#
0R#
1Q#
b0 P#
1O#
1N#
0M#
1L#
0K#
1J#
0I#
0H#
0G#
0F#
0E#
0D#
0C#
0B#
b0 A#
0@#
0?#
0>#
1=#
0<#
b0 ;#
1:#
09#
b0 8#
07#
06#
15#
04#
03#
02#
01#
10#
1/#
0.#
b11 -#
b11 ,#
b0 +#
0*#
1)#
1(#
0'#
b0 &#
b0 %#
0$#
0##
0"#
0!#
1~"
1}"
b0 |"
0{"
0z"
0y"
0x"
1w"
b0 v"
0u"
1t"
b0 s"
1r"
1q"
0p"
1o"
0n"
1m"
0l"
0k"
0j"
0i"
0h"
0g"
0f"
0e"
b0 d"
0c"
0b"
0a"
1`"
0_"
b0 ^"
1]"
0\"
b0 ["
0Z"
0Y"
1X"
0W"
0V"
0U"
0T"
1S"
1R"
0Q"
b11 P"
b11 O"
b0 N"
0M"
1L"
1K"
0J"
b0 I"
b0 H"
0G"
0F"
0E"
0D"
1C"
1B"
b0 A"
0@"
0?"
0>"
0="
1<"
b0 ;"
0:"
19"
b0 8"
17"
16"
05"
14"
03"
12"
01"
00"
0/"
0."
0-"
0,"
0+"
0*"
b0 )"
0("
0'"
0&"
1%"
0$"
b0 #"
1""
0!"
b0 ~
0}
0|
1{
0z
0y
0x
0w
1v
1u
0t
b11 s
b11 r
b0 q
0p
1o
1n
0m
b0 l
b0 k
0j
0i
0h
0g
1f
1e
b0 d
0c
0b
0a
0`
1_
b0 ^
0]
1\
b0 [
1Z
1Y
0X
1W
0V
1U
0T
0S
0R
0Q
0P
0O
0N
0M
b0 L
0K
0J
0I
1H
0G
b0 F
1E
0D
b0 C
0B
0A
1@
0?
0>
0=
0<
1;
1:
09
b11 8
b11 7
b0 6
05
14
13
02
b0 1
b0 0
0/
0.
0-
0,
0+
0*
b0 )
b0 (
b0 '
b0 &
b0 %
0$
0#
0"
0!
$end
#20
1"
0L"
1M"
1*
0o
1p
1,
15
04
1.
0)#
1*#
1!
b1 '
#40
0"
0K"
1$
1L"
0M"
1+
0*
1o
0p
0n
0,
1-
03
05
14
1/
0.
1)#
0*#
0(#
0!
1#
b10 '
#60
1K"
0$
1n
0+
0-
13
0/
0)#
1!
b11 '
#80
0R"
0]"
0`"
0w"
0S"
0X"
0m"
0r"
b10 O"
1_"
1U"
1Z"
1)#
1(#
b1 I"
0!
0#
b1 %
b1 )
b100 '
#100
1"
0L"
1M"
1*
0o
1p
1,
15
04
1.
0)#
1*#
1!
b101 '
#120
0"
0K"
1L"
0M"
1+
0*
1o
0p
0n
0,
1-
03
05
14
1/
0.
1)#
0*#
0(#
0!
1#
b110 '
#140
1K"
1n
0+
0-
13
0/
0)#
1!
b111 '
#160
1\"
0t"
1f"
0~"
1S"
1X"
1m"
1r"
1a"
1b"
1g"
1h"
1y"
1z"
1!#
1"#
b1 O"
b1 ^"
b1 d"
b1 v"
b1 |"
0_"
b1 N"
b1 ["
b1 s"
0U"
0Z"
1)#
1(#
b10 I"
0!
0#
b10 %
b10 )
b1000 '
#180
1"
0L"
1M"
1*
0o
1p
1,
15
04
1.
0)#
1*#
1!
b1001 '
#200
0"
0K"
1L"
0M"
1+
0*
1o
0p
0n
0,
1-
03
05
14
1/
0.
1)#
0*#
0(#
0!
1#
b1010 '
#220
1K"
1n
0+
0-
13
0/
0)#
1!
b1011 '
#240
0\"
0f"
0}"
0S"
0X"
0m"
0r"
b0 O"
1e"
1U"
1Z"
1)#
1(#
b11 I"
0!
0#
b11 %
b11 )
b1100 '
#260
1"
0L"
1M"
1*
0o
1p
1,
15
04
1.
0)#
1*#
1!
b1101 '
#280
0"
0K"
1L"
0M"
1+
0*
1o
0p
0n
0,
1-
03
05
14
1/
0.
1)#
0*#
0(#
0!
1#
b1110 '
#300
1K"
1n
0+
0-
13
0/
0)#
1!
b1111 '
#320
0u
1R"
0""
1]"
1t"
0%"
0<"
1`"
1w"
1~"
1}"
0v
0{
02"
07"
1S"
1X"
1m"
1r"
0a"
0b"
0g"
0h"
0y"
0z"
0!#
0"#
b10 r
1$"
b11 O"
b0 ^"
b0 d"
b0 v"
b0 |"
0e"
1x
1}
b0 N"
b0 ["
b0 s"
0U"
0Z"
1)#
1(#
b1 l
b0 I"
0!
0#
b100 %
b100 )
b10000 '
#340
1"
0L"
1M"
1*
0o
1p
1,
15
04
1.
0)#
1*#
1!
b10001 '
#360
0"
1L"
0M"
0*
1o
0p
0n
0,
1-
03
05
14
1/
0.
1)#
0*#
0(#
0!
1#
b10010 '
#380
1n
0-
13
0/
0)#
1!
b10011 '
#400
0R"
0]"
0`"
0w"
0S"
0X"
0m"
0r"
b10 O"
1_"
1U"
1Z"
1)#
1(#
b1 I"
0!
0#
b101 %
b101 )
b10100 '
#420
1"
0L"
1M"
1*
0o
1p
1,
15
04
1.
0)#
1*#
1!
b10101 '
#440
0"
1L"
0M"
0*
1o
0p
0n
0,
1-
03
05
14
1/
0.
1)#
0*#
0(#
0!
1#
b10110 '
#460
1n
0-
13
0/
0)#
1!
b10111 '
#480
1\"
0t"
1f"
0~"
1S"
1X"
1m"
1r"
1a"
1b"
1g"
1h"
1y"
1z"
1!#
1"#
b1 O"
b1 ^"
b1 d"
b1 v"
b1 |"
0_"
b1 N"
b1 ["
b1 s"
0U"
0Z"
1)#
1(#
b10 I"
0!
0#
b110 %
b110 )
b11000 '
#500
1"
0L"
1M"
1*
0o
1p
1,
15
04
1.
0)#
1*#
1!
b11001 '
#520
0"
1L"
0M"
0*
1o
0p
0n
0,
1-
03
05
14
1/
0.
1)#
0*#
0(#
0!
1#
b11010 '
#540
1n
0-
13
0/
0)#
1!
b11011 '
#560
0\"
0f"
0}"
0S"
0X"
0m"
0r"
b0 O"
1e"
1U"
1Z"
1)#
1(#
b11 I"
0!
0#
b111 %
b111 )
b11100 '
#580
1"
0L"
1M"
1*
0o
1p
1,
15
04
1.
0)#
1*#
1!
b11101 '
#600
0"
1L"
0M"
0*
1o
0p
0n
0,
1-
03
05
14
1/
0.
1)#
0*#
0(#
0!
1#
b11110 '
#620
1n
0-
13
0/
0)#
1!
b11111 '
#640
1R"
1!"
09"
1]"
1t"
1+"
0C"
1`"
1w"
1~"
1}"
1v
1{
12"
17"
1&"
1'"
1,"
1-"
1>"
1?"
1D"
1E"
1S"
1X"
1m"
1r"
0a"
0b"
0g"
0h"
0y"
0z"
0!#
0"#
b1 r
b1 #"
b1 )"
b1 ;"
b1 A"
0$"
b11 O"
b0 ^"
b0 d"
b0 v"
b0 |"
0e"
b1 q
b1 ~
b1 8"
0x
0}
b0 N"
b0 ["
b0 s"
0U"
0Z"
1)#
1(#
b10 l
b0 I"
0!
0#
b1000 %
b1000 )
b100000 '
#660
1"
0L"
1M"
1*
0o
1p
1,
15
04
1.
0)#
1*#
1!
b100001 '
#680
0"
1L"
0M"
0*
1o
0p
0n
0,
1-
03
05
14
1/
0.
1)#
0*#
0(#
0!
1#
b100010 '
#700
1n
0-
13
0/
0)#
1!
b100011 '
#720
0R"
0]"
0`"
0w"
0S"
0X"
0m"
0r"
b10 O"
1_"
1U"
1Z"
1)#
1(#
b1 I"
0!
0#
b1001 %
b1001 )
b100100 '
